MANIFEST.in
README.md
__init__.py
setup.py
version
batchx/__init__.py
batchx/admin_pb2.py
batchx/admin_pb2_grpc.py
batchx/alert_pb2.py
batchx/alert_pb2_grpc.py
batchx/audit_pb2.py
batchx/audit_pb2_grpc.py
batchx/auth_pb2.py
batchx/auth_pb2_grpc.py
batchx/billing_pb2.py
batchx/billing_pb2_grpc.py
batchx/bx.py
batchx/common_pb2.py
batchx/common_pb2_grpc.py
batchx/consumer_pb2.py
batchx/consumer_pb2_grpc.py
batchx/docker_pb2.py
batchx/docker_pb2_grpc.py
batchx/environment_pb2.py
batchx/environment_pb2_grpc.py
batchx/filesystem_pb2.py
batchx/filesystem_pb2_grpc.py
batchx/health_pb2.py
batchx/health_pb2_grpc.py
batchx/image_pb2.py
batchx/image_pb2_grpc.py
batchx/job_pb2.py
batchx/job_pb2_grpc.py
batchx/log_pb2.py
batchx/log_pb2_grpc.py
batchx/organization_pb2.py
batchx/organization_pb2_grpc.py
batchx/picture_pb2.py
batchx/picture_pb2_grpc.py
batchx/profile_pb2.py
batchx/profile_pb2_grpc.py
batchx/provider_pb2.py
batchx/provider_pb2_grpc.py
batchx/tag_pb2.py
batchx/tag_pb2_grpc.py
batchx/token_pb2.py
batchx/token_pb2_grpc.py
batchx/user_pb2.py
batchx/user_pb2_grpc.py
batchx.egg-info/PKG-INFO
batchx.egg-info/SOURCES.txt
batchx.egg-info/dependency_links.txt
batchx.egg-info/requires.txt
batchx.egg-info/top_level.txt