Metadata-Version: 2.1
Name: batchx
Version: 9.4.0
Summary: Batchx Python API
Home-page: https://github.com/batchx/api
Author: Batchx
Author-email: dev@batchx.com
License: UNKNOWN
Platform: UNKNOWN
